[
  { "title": "Footstep Concrete 01", "category": "Footsteps", "audioUrl": "https://example.com/s01.mp3", "downloadUrl": "https://example.com/s01.mp3", "tags": "footstep concrete", "origin": "Human" },
  { "title": "Footstep Concrete 02", "category": "Footsteps", "audioUrl": "https://example.com/s02.mp3", "downloadUrl": "https://example.com/s02.mp3", "tags": "footstep concrete", "origin": "Human" },
  { "title": "Footstep Grass 01", "category": "Footsteps", "audioUrl": "https://example.com/s03.mp3", "downloadUrl": "https://example.com/s03.mp3", "tags": "footstep grass", "origin": "AI" },
  { "title": "Footstep Wood 01", "category": "Footsteps", "audioUrl": "https://example.com/s04.mp3", "downloadUrl": "https://example.com/s04.mp3", "tags": "footstep wood", "origin": "Human" },
  { "title": "Footstep Gravel 01", "category": "Footsteps", "audioUrl": "https://example.com/s05.mp3", "downloadUrl": "https://example.com/s05.mp3", "tags": "footstep gravel", "origin": "AI" },
  { "title": "Footstep Sand 01", "category": "Footsteps", "audioUrl": "https://example.com/s06.mp3", "downloadUrl": "https://example.com/s06.mp3", "tags": "footstep sand", "origin": "Human" },
  { "title": "Footstep Carpet 01", "category": "Footsteps", "audioUrl": "https://example.com/s07.mp3", "downloadUrl": "https://example.com/s07.mp3", "tags": "footstep carpet", "origin": "AI" },
  { "title": "Footstep Stairs 01", "category": "Footsteps", "audioUrl": "https://example.com/s08.mp3", "downloadUrl": "https://example.com/s08.mp3", "tags": "footstep stairs", "origin": "Human" },
  { "title": "Footstep Metal 01", "category": "Footsteps", "audioUrl": "https://example.com/s09.mp3", "downloadUrl": "https://example.com/s09.mp3", "tags": "footstep metal", "origin": "AI" },
  { "title": "Footstep Tile 01", "category": "Footsteps", "audioUrl": "https://example.com/s10.mp3", "downloadUrl": "https://example.com/s10.mp3", "tags": "footstep tile", "origin": "Human" },

  { "title": "Door Creak 01", "category": "Objects", "audioUrl": "https://example.com/s11.mp3", "downloadUrl": "https://example.com/s11.mp3", "tags": "door creak wood", "origin": "Human" },
  { "title": "Door Slam 01", "category": "Objects", "audioUrl": "https://example.com/s12.mp3", "downloadUrl": "https://example.com/s12.mp3", "tags": "door slam", "origin": "AI" },
  { "title": "Glass Break 01", "category": "Objects", "audioUrl": "https://example.com/s13.mp3", "downloadUrl": "https://example.com/s13.mp3", "tags": "glass break", "origin": "Human" },
  { "title": "Chair Drag 01", "category": "Objects", "audioUrl": "https://example.com/s14.mp3", "downloadUrl": "https://example.com/s14.mp3", "tags": "chair drag", "origin": "AI" },
  { "title": "Paper Rustle 01", "category": "Objects", "audioUrl": "https://example.com/s15.mp3", "downloadUrl": "https://example.com/s15.mp3", "tags": "paper rustle", "origin": "Human" },
  { "title": "Book Drop 01", "category": "Objects", "audioUrl": "https://example.com/s16.mp3", "downloadUrl": "https://example.com/s16.mp3", "tags": "book drop", "origin": "AI" },
  { "title": "Keyboard Typing 01", "category": "Objects", "audioUrl": "https://example.com/s17.mp3", "downloadUrl": "https://example.com/s17.mp3", "tags": "keyboard typing", "origin": "Human" },
  { "title": "Light Switch 01", "category": "Objects", "audioUrl": "https://example.com/s18.mp3", "downloadUrl": "https://example.com/s18.mp3", "tags": "light switch click", "origin": "AI" },
  { "title": "Drawer Open 01", "category": "Objects", "audioUrl": "https://example.com/s19.mp3", "downloadUrl": "https://example.com/s19.mp3", "tags": "drawer open", "origin": "Human" },
  { "title": "Bottle Drop 01", "category": "Objects", "audioUrl": "https://example.com/s20.mp3", "downloadUrl": "https://example.com/s20.mp3", "tags": "bottle drop", "origin": "AI" },

  { "title": "Wind Ambience 01", "category": "Ambience", "audioUrl": "https://example.com/s21.mp3", "downloadUrl": "https://example.com/s21.mp3", "tags": "wind ambience", "origin": "Human" },
  { "title": "Rain Ambience 01", "category": "Ambience", "audioUrl": "https://example.com/s22.mp3", "downloadUrl": "https://example.com/s22.mp3", "tags": "rain ambience", "origin": "AI" },
  { "title": "Forest Ambience 01", "category": "Ambience", "audioUrl": "https://example.com/s23.mp3", "downloadUrl": "https://example.com/s23.mp3", "tags": "forest birds", "origin": "Human" },
  { "title": "City Ambience 01", "category": "Ambience", "audioUrl": "https://example.com/s24.mp3", "downloadUrl": "https://example.com/s24.mp3", "tags": "city traffic", "origin": "AI" },
  { "title": "Room Tone 01", "category": "Ambience", "audioUrl": "https://example.com/s25.mp3", "downloadUrl": "https://example.com/s25.mp3", "tags": "room tone", "origin": "Human" },
  { "title": "Night Ambience 01", "category": "Ambience", "audioUrl": "https://example.com/s26.mp3", "downloadUrl": "https://example.com/s26.mp3", "tags": "night crickets", "origin": "AI" },
  { "title": "Beach Waves 01", "category": "Ambience", "audioUrl": "https://example.com/s27.mp3", "downloadUrl": "https://example.com/s27.mp3", "tags": "ocean waves", "origin": "Human" },
  { "title": "Thunder 01", "category": "Ambience", "audioUrl": "https://example.com/s28.mp3", "downloadUrl": "https://example.com/s28.mp3", "tags": "thunder storm", "origin": "AI" },
  { "title": "Wind Gust 01", "category": "Ambience", "audioUrl": "https://example.com/s29.mp3", "downloadUrl": "https://example.com/s29.mp3", "tags": "wind gust", "origin": "Human" },
  { "title": "Market Ambience 01", "category": "Ambience", "audioUrl": "https://example.com/s30.mp3", "downloadUrl": "https://example.com/s30.mp3", "tags": "market crowd", "origin": "AI" },

  { "title": "Punch Impact 01", "category": "Impacts", "audioUrl": "https://example.com/s31.mp3", "downloadUrl": "https://example.com/s31.mp3", "tags": "punch impact", "origin": "Human" },
  { "title": "Metal Hit 01", "category": "Impacts", "audioUrl": "https://example.com/s32.mp3", "downloadUrl": "https://example.com/s32.mp3", "tags": "metal hit", "origin": "AI" },
  { "title": "Wood Hit 01", "category": "Impacts", "audioUrl": "https://example.com/s33.mp3", "downloadUrl": "https://example.com/s33.mp3", "tags": "wood hit", "origin": "Human" },
  { "title": "Explosion 01", "category": "Impacts", "audioUrl": "https://example.com/s34.mp3", "downloadUrl": "https://example.com/s34.mp3", "tags": "explosion blast", "origin": "AI" },
  { "title": "Crash 01", "category": "Impacts", "audioUrl": "https://example.com/s35.mp3", "downloadUrl": "https://example.com/s35.mp3", "tags": "crash impact", "origin": "Human" },
  { "title": "Drop Heavy 01", "category": "Impacts", "audioUrl": "https://example.com/s36.mp3", "downloadUrl": "https://example.com/s36.mp3", "tags": "heavy drop", "origin": "AI" },
  { "title": "Clap 01", "category": "Impacts", "audioUrl": "https://example.com/s37.mp3", "downloadUrl": "https://example.com/s37.mp3", "tags": "clap hands", "origin": "Human" },
  { "title": "Table Knock 01", "category": "Impacts", "audioUrl": "https://example.com/s38.mp3", "downloadUrl": "https://example.com/s38.mp3", "tags": "table knock", "origin": "AI" },
  { "title": "Rock Fall 01", "category": "Impacts", "audioUrl": "https://example.com/s39.mp3", "downloadUrl": "https://example.com/s39.mp3", "tags": "rock fall", "origin": "Human" },
  { "title": "Sword Clash 01", "category": "Impacts", "audioUrl": "https://example.com/s40.mp3", "downloadUrl": "https://example.com/s40.mp3", "tags": "sword clash metal", "origin": "AI" },

  { "title": "Car Engine Start 01", "category": "Vehicles", "audioUrl": "https://example.com/s41.mp3", "downloadUrl": "https://example.com/s41.mp3", "tags": "car engine start", "origin": "Human" },
  { "title": "Car Pass By 01", "category": "Vehicles", "audioUrl": "https://example.com/s42.mp3", "downloadUrl": "https://example.com/s42.mp3", "tags": "car pass", "origin": "AI" },
  { "title": "Motorcycle Rev 01", "category": "Vehicles", "audioUrl": "https://example.com/s43.mp3", "downloadUrl": "https://example.com/s43.mp3", "tags": "motorcycle rev", "origin": "Human" },
  { "title": "Helicopter 01", "category": "Vehicles", "audioUrl": "https://example.com/s44.mp3", "downloadUrl": "https://example.com/s44.mp3", "tags": "helicopter fly", "origin": "AI" },
  { "title": "Train Pass 01", "category": "Vehicles", "audioUrl": "https://example.com/s45.mp3", "downloadUrl": "https://example.com/s45.mp3", "tags": "train pass", "origin": "Human" },
  { "title": "Boat Engine 01", "category": "Vehicles", "audioUrl": "https://example.com/s46.mp3", "downloadUrl": "https://example.com/s46.mp3", "tags": "boat engine", "origin": "AI" },
  { "title": "Bicycle Bell 01", "category": "Vehicles", "audioUrl": "https://example.com/s47.mp3", "downloadUrl": "https://example.com/s47.mp3", "tags": "bicycle bell", "origin": "Human" },
  { "title": "Airplane Flyover 01", "category": "Vehicles", "audioUrl": "https://example.com/s48.mp3", "downloadUrl": "https://example.com/s48.mp3", "tags": "airplane flyover", "origin": "AI" },
  { "title": "Truck Horn 01", "category": "Vehicles", "audioUrl": "https://example.com/s49.mp3", "downloadUrl": "https://example.com/s49.mp3", "tags": "truck horn", "origin": "Human" },
  { "title": "Car Brake 01", "category": "Vehicles", "audioUrl": "https://example.com/s50.mp3", "downloadUrl": "https://example.com/s50.mp3", "tags": "car brake", "origin": "AI" },

  { "title": "Breathing 01", "category": "Body", "audioUrl": "https://example.com/s51.mp3", "downloadUrl": "https://example.com/s51.mp3", "tags": "breathing human", "origin": "Human" },
  { "title": "Heartbeat 01", "category": "Body", "audioUrl": "https://example.com/s52.mp3", "downloadUrl": "https://example.com/s52.mp3", "tags": "heartbeat", "origin": "AI" },
  { "title": "Cough 01", "category": "Body", "audioUrl": "https://example.com/s53.mp3", "downloadUrl": "https://example.com/s53.mp3", "tags": "cough", "origin": "Human" },
  { "title": "Laugh 01", "category": "Body", "audioUrl": "https://example.com/s54.mp3", "downloadUrl": "https://example.com/s54.mp3", "tags": "laugh", "origin": "AI" },
  { "title": "Dog Bark 01", "category": "Animals", "audioUrl": "https://example.com/s55.mp3", "downloadUrl": "https://example.com/s55.mp3", "tags": "dog bark", "origin": "Human" },
  { "title": "Cat Meow 01", "category": "Animals", "audioUrl": "https://example.com/s56.mp3", "downloadUrl": "https://example.com/s56.mp3", "tags": "cat meow", "origin": "AI" },
  { "title": "Bird Chirp 01", "category": "Animals", "audioUrl": "https://example.com/s57.mp3", "downloadUrl": "https://example.com/s57.mp3", "tags": "bird chirp", "origin": "Human" },
  { "title": "Horse Neigh 01", "category": "Animals", "audioUrl": "https://example.com/s58.mp3", "downloadUrl": "https://example.com/s58.mp3", "tags": "horse neigh", "origin": "AI" },
  { "title": "Rooster Crow 01", "category": "Animals", "audioUrl": "https://example.com/s59.mp3", "downloadUrl": "https://example.com/s59.mp3", "tags": "rooster crow", "origin": "Human" },
  { "title": "Wolf Howl 01", "category": "Animals", "audioUrl": "https://example.com/s60.mp3", "downloadUrl": "https://example.com/s60.mp3", "tags": "wolf howl", "origin": "AI" }
]